[
  {
    "TypeName": "Kub 1S91 str",
    "DisplayName": null,
    "MapMarker": null,
    "Information": "RWR=6 HARM=108",
    "MainInGroup": false,
    "KneeboardDirectory": null
  },
  {
    "TypeName": "SNR_75V",
    "DisplayName": null,
    "MapMarker": null,
    "Information": "RWR=2 HARM=126",
    "MainInGroup": true,
    "KneeboardDirectory": null
  },
  {
    "TypeName": "S-300PS 40B6M tr",
    "DisplayName": null,
    "MapMarker": null,
    "Information": "RWR=10 HARM=110",
    "MainInGroup": false,
    "KneeboardDirectory": null
  },
  {
    "TypeName": "ZSU-23-4 Shilka",
    "DisplayName": null,
    "MapMarker": null,
    "Information": "RWR=A HARM=121",
    "MainInGroup": false,
    "KneeboardDirectory": null
  },
  {
    "TypeName": "p-19 s-125 sr",
    "DisplayName": null,
    "MapMarker": null,
    "Information": "RWR=S/FF HARM=122",
    "MainInGroup": false,
    "KneeboardDirectory": null
  },
  {
    "TypeName": "Dog Ear radar",
    "DisplayName": null,
    "MapMarker": null,
    "Information": "RWR=DE HARM=109",
    "MainInGroup": false,
    "KneeboardDirectory": null
  },
  {
    "TypeName": "1L13 EWR",
    "DisplayName": null,
    "MapMarker": null,
    "Information": "RWR=S HARM=101",
    "MainInGroup": false,
    "KneeboardDirectory": null
  },
  {
    "TypeName": "S-300PS 40B6MD sr",
    "DisplayName": null,
    "MapMarker": null,
    "Information": "RWR=CS HARM=103",
    "MainInGroup": false,
    "KneeboardDirectory": null
  },
  {
    "TypeName": "S-300PS 64H6E sr",
    "DisplayName": null,
    "MapMarker": null,
    "Information": "RWR=BB HARM=104",
    "MainInGroup": false,
    "KneeboardDirectory": null
  },
  {
    "TypeName": "Osa 9A33 ln",
    "DisplayName": null,
    "MapMarker": null,
    "Information": "RWR=8 HARM=117",
    "MainInGroup": false,
    "KneeboardDirectory": null
  },
  {
    "TypeName": "55G6 EWR",
    "DisplayName": null,
    "MapMarker": null,
    "Information": "RWR=S HARM=102",
    "MainInGroup": false,
    "KneeboardDirectory": null
  },
  {
    "TypeName": "Tor 9A331",
    "DisplayName": null,
    "MapMarker": null,
    "Information": "RWR=15 HARM=119",
    "MainInGroup": false,
    "KneeboardDirectory": null
  }
]