[
  {
    "Type": "1L13",
    "Description": "1L13 EWR 'Box Spring'",
    "MapMarker": "P91000083",
    "Information": "RWR=S HARM=101",
    "Function": "AAW"
  },
  {
    "Type": "55G6",
    "Description": "55G6 EWR 'Tall Rack'",
    "MapMarker": "P91000083",
    "Information": "RWR=S HARM=102",
    "Function": "AAW"
  },

  {
    "Type": "p-19 s-125 sr",
    "Description": "P19 SR 'Flat Face'",
    "MapMarker": "P91000083",
    "Information": "RWR=S/FF HARM=122",
    "Function": "AAW"
  },

  {
    "Type": "SNR_75V",
    "Description": "SNR-75 TR 'Fan Song'",
    "MapMarker": "P91000083",
    "Information": "RWR=2 HARM=126",
    "Function": "AAW"
  },
  {
    "Type": "S_75M_Volhov",
    "Description": "S-75/SA-2 LN 'Guideline'",
    "MapMarker": "P91000080",
    "Function": "AAW"
  },
  {
    "Type": "Kub 1S91 str",
    "Description": "Kub 1S91 STR 'Straight Flush'",
    "MapMarker": "P91000083",
    "Information": "RWR=6 HARM=108",
    "Function": "AAW"
  },
  {
    "Type": "Kub 2P25 ln",
    "Description": "2K12/SA-6 LN 'Gainful'",
    "MapMarker": "P91000080",
    "Function": "AAW"
  },
 
  {
    "Type": "Dog Ear radar",
    "Description": "9S80M1 SR 'Dog Ear'",
    "MapMarker": "P91000083",
    "Information": "RWR=DE HARM=109",
    "Function": "AAW"
  },
  {
    "Type": "Osa 9A33 ln",
    "Description": "9K33/SA-8 'Gecko'",
    "MapMarker": "P91000018",
    "Information": "RWR=8 HARM=117",
    "Function": "AAW"
  },
  
  {
     "Type": "S-300PS 54K6 cp",
     "Description": "S-300PS/SA-10B CP",
     "MapMarker": "P91000047",
     "Function": "AAW"
  },
  {
    "Type": "S-300PS 64H6E sr",
    "Description": "64H6E TR 'Big Bird'",
    "Marker": "P91000083",
    "Information": "RWR=BB HARM=104",
    "Function": "AAW"
  },
  {
    "Type": "S-300PS 40B6M tr",
    "Description": "30N6E TR 'Flap Lid'",
    "MapMarker": "P91000083",
    "Information": "RWR=10 HARM=110",
    "Function": "AAW"
  },
  {
    "Type": "S-300PS 40B6MD sr",
    "Description": "S-300PS/SA-10B SR 76N6 'Clam Shell'",
    "MapMarker": "P91000083",
    "Information": "RWR=CS HARM=103",
    "Function": "AAW"
  },
  {
    "Type": "S-300PS 5P85D ln",
    "Description": "S-300PS/SA-10B TEL 'Grumble'",
    "MapMarker": "P91000080",
    "Function": "AAW"
  },

  {
    "Type": "Tor 9A331",
    "Description": "Tor 9A331 STR 'Scrum Half'",
    "MapMarker": "P91000018",
    "Information": "RWR=15 HARM=119",
    "Function": "AAW"
  },

  {
    "Type": "ZSU-23-4 Shilka",
    "Description": "ZSU-23-4 Shilka",
    "MapMarker": "P91000017",
    "Information": "RWR=A HARM=121",
    "Function": "AAW"
  },
   
  {
    "Type": "FA-18C_hornet",
    "MapMarker": "P91000024",
    "KneeboardFolder": "FA-18C_hornet"
  }
]